capnp_stub_gen/__init__.py
capnp_stub_gen/cli.py
capnp_stub_gen/generator.py
capnp_stub_gen/py.typed
capnp_stub_gen/types.py
capnp_stub_gen-0.1.3.dist-info/METADATA
capnp_stub_gen-0.1.3.dist-info/WHEEL
capnp_stub_gen-0.1.3.dist-info/entry_points.txt
capnp_stub_gen-0.1.3.dist-info/licenses/LICENSE
capnp_stub_gen-0.1.3.dist-info/RECORD
