Metadata-Version: 2.4
Name: capnp-stub-gen
Version: 0.1.3
Summary: Generate Python type stubs from Cap'n Proto schema files
License-Expression: MIT
License-File: LICENSE
Keywords: capnp,capnproto,stubs,typing,pyi,type-hints
Author: KaiErikNiermann
Author-email: kai.niermann@gmail.com
Requires-Python: >=3.14
Classifier: Development Status :: 4 - Beta
Classifier: Intended Audience :: Developers
Classifier: License :: OSI Approved :: MIT License
Classifier: Operating System :: OS Independent
Classifier: Programming Language :: Python :: 3
Classifier: Programming Language :: Python :: 3.14
Classifier: Topic :: Software Development :: Code Generators
Classifier: Topic :: Software Development :: Libraries :: Python Modules
Classifier: Typing :: Typed
Provides-Extra: dev
Requires-Dist: pycapnp (>=2.0.0)
Requires-Dist: pyright (>=1.1.0) ; extra == "dev"
Requires-Dist: pytest (>=8.0.0) ; extra == "dev"
Requires-Dist: pytest-cov (>=6.0.0) ; extra == "dev"
Requires-Dist: ruff (>=0.8.0) ; extra == "dev"
Requires-Dist: typer (>=0.15.0)
Project-URL: Homepage, https://github.com/KaiErikNiermann/capnp-stub-gen
Project-URL: Issues, https://github.com/KaiErikNiermann/capnp-stub-gen/issues
Project-URL: Repository, https://github.com/KaiErikNiermann/capnp-stub-gen
